hmscalc/__init__.py
hmscalc/exceptions.py
hmscalc/hms_time.py
hmscalc-0.2.0.dist-info/LICENSE
hmscalc-0.2.0.dist-info/METADATA
hmscalc-0.2.0.dist-info/WHEEL
hmscalc-0.2.0.dist-info/RECORD
