Metadata-Version: 2.3
Name: hmscalc
Version: 0.2.0
Summary: A Python library for performing arithmetic with HH:MM[:SS] formatted time strings.
License: MIT
Author: M0209
Author-email: masanorimurakoshi0209@gmail.com
Requires-Python: >=3.9,<4.0
Classifier: License :: OSI Approved :: MIT License
Classifier: Programming Language :: Python :: 3
Classifier: Programming Language :: Python :: 3.9
Classifier: Programming Language :: Python :: 3.10
Classifier: Programming Language :: Python :: 3.11
Classifier: Programming Language :: Python :: 3.12
Classifier: Programming Language :: Python :: 3.13
